odoo/addons/stock_analytic_rule/README.rst
odoo/addons/stock_analytic_rule/__init__.py
odoo/addons/stock_analytic_rule/__manifest__.py
odoo/addons/stock_analytic_rule/i18n/ca.po
odoo/addons/stock_analytic_rule/i18n/es.po
odoo/addons/stock_analytic_rule/i18n/it.po
odoo/addons/stock_analytic_rule/i18n/stock_analytic_rule.pot
odoo/addons/stock_analytic_rule/models/__init__.py
odoo/addons/stock_analytic_rule/models/account_analytic_line.py
odoo/addons/stock_analytic_rule/models/product_category.py
odoo/addons/stock_analytic_rule/models/stock_analytic_rule.py
odoo/addons/stock_analytic_rule/models/stock_move.py
odoo/addons/stock_analytic_rule/readme/CONTRIBUTORS.md
odoo/addons/stock_analytic_rule/readme/DESCRIPTION.md
odoo/addons/stock_analytic_rule/readme/USAGE.md
odoo/addons/stock_analytic_rule/security/analytic_security.xml
odoo/addons/stock_analytic_rule/security/ir.model.access.csv
odoo/addons/stock_analytic_rule/static/description/icon.png
odoo/addons/stock_analytic_rule/static/description/index.html
odoo/addons/stock_analytic_rule/tests/__init__.py
odoo/addons/stock_analytic_rule/tests/test_stock_analytic_rule.py
odoo/addons/stock_analytic_rule/views/account_analytic_line_views.xml
odoo/addons/stock_analytic_rule/views/product_category_views.xml
odoo/addons/stock_analytic_rule/views/stock_analytic_model.xml
odoo_addon_stock_analytic_rule-17.0.1.0.0.4.dist-info/METADATA
odoo_addon_stock_analytic_rule-17.0.1.0.0.4.dist-info/WHEEL
odoo_addon_stock_analytic_rule-17.0.1.0.0.4.dist-info/top_level.txt
odoo_addon_stock_analytic_rule-17.0.1.0.0.4.dist-info/RECORD
